slobad/__init__.py
slobad/_wrappers.py
slobad/slobad.py
slobad-0.0.3.dist-info/METADATA
slobad-0.0.3.dist-info/WHEEL
slobad-0.0.3.dist-info/top_level.txt
slobad-0.0.3.dist-info/RECORD
