Metadata-Version: 2.1
Name: slobad
Version: 0.0.3
Summary: Caching of Pandas DataFrames
Home-page: https://gitlab.com/slobad/slobad
Maintainer: slobad developers
Maintainer-email: slobadpy@gmail.com
License: MIT
Platform: UNKNOWN
Classifier: License :: OSI Approved :: MIT License
Classifier: Programming Language :: Python :: 3.6
Classifier: Programming Language :: Python :: 3.7
Requires-Python: >=3.6
Requires-Dist: pandas (>=0.19)
Requires-Dist: pyarrow
